Verilog/03_mux_bilibili/mux.v
/*功能描述
    sel=00 输出a&b
    sel=01 输出a|b
    sel=10 输出a^b
    sel=11 输出~(a^b)
 
    输入：3个 a b sel;其中sel位宽为2
    输出：1个 y
*/
module mux(
        input a,b,
        input [1:0]sel,

        output y
    );

    //always语句赋值用reg
    reg y;

    always @(*) begin
        case (sel)
            2'b 00:
                y=a&b;
            2'b 01:
                y=a|b;
            2'b 10:
                y=a^b;
            2'b 11:
                y=~(a^b);
            endcase
    end

endmodule

Verilog/03_mux_bilibili/testbench.v
/*
    对a,b,[1:0]sel整体赋值，这样代码会更简洁
    通过声明变量，调用模块，连接接口的方法在testbench中调用mux器
*/
module testbench();
    reg [3:0]sel_b_a;
    wire y;
    //调用mux_bilibili 接线
    mux mux_01(
            .a(sel_b_a[0]),
            .b(sel_b_a[1]),
            .sel(sel_b_a[3:2]),
            .y(y)
        );

    //激励1：生成文件和信号
    initial begin
        $dumpfile("reference.vcd");
        $dumpvars;
    end
    //激励2：控制信号电平
    initial begin
        sel_b_a=4'b0000;
        #200 $finish;
    end
    //和激励2并行运行，使得在200ns内每10ns sel_a_b就自增一次
    always #10 begin
        sel_b_a<=sel_b_a+1;
    end

endmodule

Verilog/03_mux_bilibili/reference.vcd
$date
	Sat Jun 24 15:40:13 2023
$end
$version
	Icarus Verilog
$end
$timescale
	1s
$end
$scope module testbench $end
$var wire 1 ! y $end
$var reg 4 " sel_b_a [3:0] $end
$scope module mux_01 $end
$var wire 1 # a $end
$var wire 1 $ b $end
$var wire 2 % sel [1:0] $end
$var reg 1 ! y $end
$upscope $end
$upscope $end
$enddefinitions $end
#0
$dumpvars
b0 %
0$
0#
b0 "
0!
$end
#10
1#
b1 "
#20
0#
1$
b10 "
#30
1!
1#
b11 "
#40
0!
0#
0$
b1 %
b100 "
#50
1!
1#
b101 "
#60
0#
1$
b110 "
#70
1#
b111 "
#80
0!
0#
0$
b10 %
b1000 "
#90
1!
1#
b1001 "
#100
0#
1$
b1010 "
#110
0!
1#
b1011 "
#120
1!
0#
0$
b11 %
b1100 "
#130
0!
1#
b1101 "
#140
0#
1$
b1110 "
#150
1!
1#
b1111 "
#160
0!
0#
0$
b0 %
b0 "
#170
1#
b1 "
#180
0#
1$
b10 "
#190
1!
1#
b11 "
#200
0!
0#
0$
b1 %
b100 "
