Verilog/05_Pre/13_长字符串格式判断2/cpu_checker.v
`define S_00 5'd0
`define S_01 5'd1
`define S_02 5'd2
`define S_03 5'd3
`define S_04 5'd4
`define S_05 5'd5
`define S_06 5'd6
`define S_07 5'd7
`define S_08 5'd8
`define S_09 5'd9
`define S_10 5'd10
`define S_11 5'd11
`define S_12 5'd12
`define S_13 5'd13
`define S_14 5'd14
`define S_15 5'd15
`define S_16 5'd16
`define S_17 5'd17
`define S_18 5'd18
`define S_19 5'd19
`define S_20 5'd20
`define S_25 5'd25
`define S_27 5'd27
`define S_29 5'd29

module cpu_checker (
    input clk,
    input reset,
    input [7:0]char,
    output [1:0]format_type
);
    
    reg [4:0]my_states;
    reg [2:0]cnt_up8;
    reg [1:0]cnt_up4;

    assign format_type = (my_states==`S_10)?2'b01:
                        (my_states==`S_20)?2'b10:
                        2'b00;

    always @(posedge clk) begin
        if(reset)begin
            my_states<=`S_00;
            cnt_up8<=3'd0;
            cnt_up4<=2'd0;
        end
        else begin
            case (my_states)
                `S_00: begin
                    my_states<=(char=="^")?`S_01:
                                `S_00;
                end
                `S_01:begin
                    if(char>="0"&&char<="9")begin
                        my_states<=`S_02;
                        cnt_up4<=2'd1;
                    end
                    else begin
                        my_states<=(char=="^")?`S_01:
                                `S_00;
                    end
                end
                `S_02:begin
                    if(char>="0"&&char<="9")begin
                        cnt_up4<=cnt_up4+2'd1;
                        if(cnt_up4==2'd0)my_states<=`S_00;
                        else my_states<=`S_02;
                    end
                    else if(char=="@")begin
                        my_states<=`S_25;
                        cnt_up4<=2'd0;
                        cnt_up8<=3'd0;
                    end
                    else begin
                        my_states<=(char=="^")?`S_01:
                                `S_00;
                    end
                end
                `S_25:begin
                    if(((char>="0")&&(char<="9"))||((char>="a")&&(char<="f")))begin
                        cnt_up8<=3'd1;
                        my_states<=`S_03;
                    end
                    else begin
                        my_states<=(char=="^")?`S_01:
                                `S_00;
                    end
                end
                `S_03:begin
                    if(((char>="0")&&(char<="9"))||((char>="a")&&(char<="f")))begin
                        cnt_up8<=cnt_up8+3'd1;
                        if(cnt_up8==3'd0)my_states<=`S_00;
                        else my_states<=`S_03;
                    end
                    else if((char==":")&&(cnt_up8==3'd0))begin
                        my_states<=`S_04;
                    end
                    else begin
                        my_states<=(char=="^")?`S_01:
                                `S_00;
                    end
                end
                `S_04:begin
                    my_states<= (char==" ")?`S_04:
                                (char=="$")?`S_27:
                                (char=="*")?`S_29:
                                (char=="^")?`S_01:
                                `S_00;
                end
                `S_27:begin
                    if(char>="0"&&char<="9")begin
                        cnt_up4<=2'd1;
                        my_states<=`S_05;
                    end
                    else begin
                        my_states<=(char=="^")?`S_01:
                                    `S_00;
                    end
                end
                `S_05:begin
                    if(char>="0"&&char<="9")begin
                        cnt_up4<=cnt_up4+2'd1;
                        if(cnt_up4==2'd0)my_states<=`S_00;
                        else my_states<=`S_05;
                    end
                    else if(char==" ")begin
                        my_states<=`S_06;
                        cnt_up4<=2'd0;
                        cnt_up8<=3'd0;
                    end
                    else if(char=="<")begin
                        my_states<=`S_07;
                        cnt_up4<=2'd0;
                        cnt_up8<=3'd0;
                    end
                    else begin
                        my_states<=(char=="^")?`S_01:
                                `S_00;
                    end
                end
                `S_06:begin
                    if(char==" ")begin
                        my_states<=`S_06;
                    end
                    else if(char=="<")begin
                        my_states<=`S_07;
                    end
                    else begin
                         my_states<=(char=="^")?`S_01:
                                `S_00;
                    end
                end
                `S_07:begin
                    if(char=="=")begin
                        my_states<=`S_08;
                    end
                    else begin
                        my_states<=(char=="^")?`S_01:
                                `S_00;
                    end
                end
                `S_08:begin
                    if(char==" ")begin
                        my_states<=`S_08;
                    end
                    else if(((char>="0")&&(char<="9"))||((char>="a")&&(char<="f")))begin
                        my_states<=`S_09;
                        cnt_up8<=3'd1;
                    end
                    else begin
                        my_states<=(char=="^")?`S_01:
                                `S_00;
                    end
                end
                `S_09:begin
                    if(((char>="0")&&(char<="9"))||((char>="a")&&(char<="f")))begin
                        cnt_up8<=cnt_up8+3'd1;
                        if(cnt_up8==3'd0)my_states<=`S_00;
                        else my_states<=`S_09;
                    end
                    else if((char=="#")&&(cnt_up8==3'd0))begin
                        my_states<=`S_10;
                    end
                    else begin
                        my_states<=(char=="^")?`S_01:
                                `S_00;
                    end
                end
                `S_10:begin
                    my_states<=(char=="^")?`S_01:
                                `S_00;
                end
                `S_29:begin
                    if(((char>="0")&&(char<="9"))||((char>="a")&&(char<="f")))begin
                        cnt_up8<=3'd1;
                        my_states<=`S_15;
                    end
                    else begin
                        my_states<=(char=="^")?`S_01:
                                `S_00;
                    end
                end
                `S_15:begin
                    if(((char>="0")&&(char<="9"))||((char>="a")&&(char<="f")))begin
                        cnt_up8<=cnt_up8+3'd1;
                        if(cnt_up8==3'd0)my_states<=`S_00;
                        else my_states<=`S_15;
                    end
                    else if((char==" ")&&(cnt_up8==3'd0))begin
                        my_states<=`S_16;
                    end
                    else if((char=="<")&&(cnt_up8==3'd0))begin
                        my_states<=`S_17;
                    end
                    else begin
                        my_states<=(char=="^")?`S_01:
                                `S_00;
                    end
                end
                `S_16:begin
                    my_states<= (char==" ")?`S_16:
                                (char=="<")?`S_17:
                                (char=="^")?`S_01:
                                `S_00;
                end
                `S_17:begin
                    my_states<= (char=="=")?`S_18:
                                (char=="^")?`S_01:
                                `S_00;
                end
                `S_18:begin
                    if(char==" ")begin
                        my_states<=`S_18;
                    end
                    else if(((char>="0")&&(char<="9"))||((char>="a")&&(char<="f")))begin
                        cnt_up8<=3'd1;
                        my_states<=`S_19;
                    end
                    else begin
                        my_states<=(char=="^")?`S_01:
                                `S_00;
                    end
                end
                `S_19:begin
                    if(((char>="0")&&(char<="9"))||((char>="a")&&(char<="f")))begin
                        cnt_up8<=cnt_up8+3'd1;
                        if(cnt_up8==3'd0)my_states<=`S_00;
                        else my_states<=`S_19;
                    end
                    else if((char=="#")&&(cnt_up8==3'd0))begin
                        my_states<=`S_20;
                    end
                    else begin
                        my_states<=(char=="^")?`S_01:
                                `S_00;
                    end
                end
                `S_20:begin
                     my_states<=(char=="^")?`S_01:
                                `S_00;
                end
                default: my_states<=`S_00;
            endcase
        end
    end

endmodule

Verilog/05_Pre/13_长字符串格式判断2/tb.v
module tb (
);
//接线
    reg clk,reset;
    reg [7:0]char;
    wire [1:0]format_type;
    cpu_checker CPU_Checker_My(
        .clk(clk),
        .reset(reset),
        .char(char),
        .format_type(format_type)
    );
//
//
//生成文件
    initial begin
        $dumpfile("reference.vcd");
        $dumpvars;
    end
//初始化
    initial begin
        clk=0;
        reset=1;
        #2;
        reset=0;
        #120 $finish;
    end
//时钟
    always #1 clk=~clk;
//控制输入
    initial begin
        #2 char="^";
        #2 char="1";
        #2 char="1";
        #2 char="1";
        #2 char="1";
        #2 char="@";
        #2 char="0";
        #2 char="0";
        #2 char="0";
        #2 char="0";
        #2 char="0";
        #2 char="0";
        #2 char="0";
        #2 char="0";
        #2 char=":";
        #2 char=" ";
        #2 char="*";
        #2 char="1";
        #2 char="1";
        #2 char="1";
        #2 char="1";
        #2 char="1";
        #2 char="1";
        #2 char="1";
        #2 char="1";
        #2 char=" ";
        #2 char="<";
        #2 char="=";
        #2 char=" ";
        #2 char="0";
        #2 char="0";
        #2 char="0";
        #2 char="0";
        #2 char="0";
        #2 char="0";
        #2 char="0";
        #2 char="0";
        #2 char="#";
    end
//
//
//
//
//
//
endmodule

Verilog/05_Pre/13_长字符串格式判断2/reference.vcd
$date
	Wed Sep 20 18:46:12 2023
$end
$version
	Icarus Verilog
$end
$timescale
	1s
$end
$scope module tb $end
$var wire 2 ! format_type [1:0] $end
$var reg 8 " char [7:0] $end
$var reg 1 # clk $end
$var reg 1 $ reset $end
$scope module CPU_Checker_My $end
$var wire 8 % char [7:0] $end
$var wire 1 # clk $end
$var wire 1 $ reset $end
$var wire 2 & format_type [1:0] $end
$var reg 2 ' cnt_up4 [1:0] $end
$var reg 3 ( cnt_up8 [2:0] $end
$var reg 5 ) my_states [4:0] $end
$upscope $end
$upscope $end
$enddefinitions $end
#0
$dumpvars
bx )
bx (
bx '
bx &
bx %
1$
0#
bx "
bx !
$end
#1
b0 !
b0 &
b0 '
b0 (
b0 )
1#
#2
0#
b1011110 "
b1011110 %
0$
#3
b1 )
1#
#4
0#
b110001 "
b110001 %
#5
b1 '
b10 )
1#
#6
0#
#7
b10 '
1#
#8
0#
#9
b11 '
1#
#10
0#
#11
b0 '
1#
#12
0#
b1000000 "
b1000000 %
#13
b11001 )
1#
#14
0#
b110000 "
b110000 %
#15
b11 )
b1 (
1#
#16
0#
#17
b10 (
1#
#18
0#
#19
b11 (
1#
#20
0#
#21
b100 (
1#
#22
0#
#23
b101 (
1#
#24
0#
#25
b110 (
1#
#26
0#
#27
b111 (
1#
#28
0#
#29
b0 (
1#
#30
0#
b111010 "
b111010 %
#31
b100 )
1#
#32
0#
b100000 "
b100000 %
#33
1#
#34
0#
b101010 "
b101010 %
#35
b11101 )
1#
#36
0#
b110001 "
b110001 %
#37
b1111 )
b1 (
1#
#38
0#
#39
b10 (
1#
#40
0#
#41
b11 (
1#
#42
0#
#43
b100 (
1#
#44
0#
#45
b101 (
1#
#46
0#
#47
b110 (
1#
#48
0#
#49
b111 (
1#
#50
0#
#51
b0 (
1#
#52
0#
b100000 "
b100000 %
#53
b10000 )
1#
#54
0#
b111100 "
b111100 %
#55
b10001 )
1#
#56
0#
b111101 "
b111101 %
#57
b10010 )
1#
#58
0#
b100000 "
b100000 %
#59
1#
#60
0#
b110000 "
b110000 %
#61
b10011 )
b1 (
1#
#62
0#
#63
b10 (
1#
#64
0#
#65
b11 (
1#
#66
0#
#67
b100 (
1#
#68
0#
#69
b101 (
1#
#70
0#
#71
b110 (
1#
#72
0#
#73
b111 (
1#
#74
0#
#75
b0 (
1#
#76
0#
b100011 "
b100011 %
#77
b10 !
b10 &
b10100 )
1#
#78
0#
#79
b0 !
b0 &
b0 )
1#
