Verilog/07_P1/L1-beginEnd匹配检查/BlockChecker.v
//用myString存输入的字符串
/*要用myString = myString<<8 | ( in | 8'h20 ) 来阻塞赋值myString，使得in的输入myString的更新同步
    样例中：在输入"n"上升沿就刷新了输出，所以用=
    如果为：在输入"n'的下降沿才刷新输出，就用<=来更新myString
*/
/*设置stackTop来判断配对情况
    stackTop<=-1 先出现了end，记录到flag中直接永远输出0，直到下一次reset
    stackTop==0 配对成功
    stackTop>=1 配对中
*/
//【注】本题会存在beginX这种情况，输入begin时有效，变成beginX后无效
//所以要考虑beginX时，对stackTop返回在上一个上升沿进栈的begin退栈
//同理也要考虑到begin必须有前导空格，即一个有效的begin其实是7个字符，" begin "
module BlockChecker (
    input clk,reset,
    input [7:0]in,
    output result
);

   //需要准备：myString、stackTop和负栈flag
   //单词数最多是2^32，所以stackTop作为配对计数器要考虑前面一直输入begin，后面一直输入end的配对情况
   //所以stackTop设置为[31:0]
   //负栈flag初始化默认为1，如果负栈后置为0，让result一直输出0直到reset
   reg [255:0]myString;
   reg [31:0]stackTop;
   reg flag;

   //对自己定义的东西要初始化
   initial begin
        myString="";
        stackTop<=0;
        flag<=1'b1;
   end

    //上升沿+复位
    always @(posedge clk,posedge reset)begin
        if(reset)begin
            myString="";
            stackTop<=0;
            flag<=1'b1;
        end
        else begin

            //更新in到myString中，然后逻辑判断
            myString = myString<<8 | (in|8'h20);

            //逻辑判断，增减栈+是否负栈
            if(myString[47:0]==" begin")stackTop <= stackTop+1;
            else if(myString[55:8]==" begin" && myString[7:0]!=" ")stackTop <= stackTop-1;
            else if(myString[31:0]==" end")stackTop <= stackTop-1;
            else if(myString[39:8]==" end" && myString[7:0]!=" ")stackTop <= stackTop+1;
            else if(myString[39:0]==" end "&&stackTop[31]==1)flag<=1'b0;
        end
    end

    assign result = ((stackTop==0)&flag);

endmodule

Verilog/07_P1/L1-beginEnd匹配检查/tb.v
module tb (
);
//接线
    reg clk,rst;
    reg [7:0]inChar;
    wire rslt;
    BlockChecker newBCR(
        .clk(clk),
        .reset(rst),
        .in(inChar),
        .result(rslt)
    );
//生成文件
    initial begin
        $dumpfile("reference.vcd");
        $dumpvars;
    end
//初始化
    initial begin
        clk=1'b0;
        rst=1'b0;
        #200 $finish;
    end
//时钟
    always #1 clk=~clk;
//控制输入
    reg [0:255]bfr;
    integer i;
    initial begin
        //初始化bfr字符串，并且把字符串开头移到bfr最低位
        bfr="a BEgIn Endc end end bEGin";
        bfr=bfr<<48;
        //for循环控制inChar
        for(i=0;i<26;i=i+1)begin
            inChar = bfr[0:7];
            bfr=bfr<<8;
            #2;
        end
        inChar=8'd0;
        #2;

        rst=1;
        #2;

        rst=0;
        bfr="a BEgIn Endc end end bEGin";
        bfr=bfr<<48;
        //for循环控制inChar
        for(i=0;i<26;i=i+1)begin
            inChar = bfr[0:7];
            bfr=bfr<<8;
            #2;
        end
        inChar=8'd0;
    end

endmodule

Verilog/07_P1/L1-beginEnd匹配检查/reference.vcd
$date
	Sun Oct 15 15:34:25 2023
$end
$version
	Icarus Verilog
$end
$timescale
	1s
$end
$scope module tb $end
$var wire 1 ! rslt $end
$var reg 256 " bfr [0:255] $end
$var reg 1 # clk $end
$var reg 8 $ inChar [7:0] $end
$var reg 1 % rst $end
$var integer 32 & i [31:0] $end
$scope module newBCR $end
$var wire 1 # clk $end
$var wire 8 ' in [7:0] $end
$var wire 1 % reset $end
$var wire 1 ! result $end
$var reg 1 ( flag $end
$var reg 256 ) myString [255:0] $end
$var reg 32 * stackTop [31:0] $end
$upscope $end
$upscope $end
$enddefinitions $end
#0
$dumpvars
b0 *
b0 )
1(
b1100001 '
b0 &
0%
b1100001 $
0#
b10000001000010010001010110011101001001011011100010000001000101011011100110010001100011001000000110010101101110011001000010000001100101011011100110010000100000011000100100010101000111011010010110111000000000000000000000000000000000000000000000000000000000 "
1!
$end
#1
b1100001 )
1#
#2
0#
b100001001000101011001110100100101101110001000000100010101101110011001000110001100100000011001010110111001100100001000000110010101101110011001000010000001100010010001010100011101101001011011100000000000000000000000000000000000000000000000000000000000000000 "
b100000 $
b100000 '
b1 &
#3
b110000100100000 )
1#
#4
0#
b100010101100111010010010110111000100000010001010110111001100100011000110010000001100101011011100110010000100000011001010110111001100100001000000110001001000101010001110110100101101110000000000000000000000000000000000000000000000000000000000000000000000000 "
b1000010 $
b1000010 '
b10 &
#5
b11000010010000001100010 )
1#
#6
0#
b110011101001001011011100010000001000101011011100110010001100011001000000110010101101110011001000010000001100101011011100110010000100000011000100100010101000111011010010110111000000000000000000000000000000000000000000000000000000000000000000000000000000000 "
b1000101 $
b1000101 '
b11 &
#7
b1100001001000000110001001100101 )
1#
#8
0#
b100100101101110001000000100010101101110011001000110001100100000011001010110111001100100001000000110010101101110011001000010000001100010010001010100011101101001011011100000000000000000000000000000000000000000000000000000000000000000000000000000000000000000 "
b1100111 $
b1100111 '
b100 &
#9
b110000100100000011000100110010101100111 )
1#
#10
0#
b110111000100000010001010110111001100100011000110010000001100101011011100110010000100000011001010110111001100100001000000110001001000101010001110110100101101110000000000000000000000000000000000000000000000000000000000000000000000000000000000000000000000000 "
b1001001 $
b1001001 '
b101 &
#11
b11000010010000001100010011001010110011101101001 )
1#
#12
0#
b10000001000101011011100110010001100011001000000110010101101110011001000010000001100101011011100110010000100000011000100100010101000111011010010110111000000000000000000000000000000000000000000000000000000000000000000000000000000000000000000000000000000000 "
b1101110 $
b1101110 '
b110 &
#13
0!
b1 *
b1100001001000000110001001100101011001110110100101101110 )
1#
#14
0#
b100010101101110011001000110001100100000011001010110111001100100001000000110010101101110011001000010000001100010010001010100011101101001011011100000000000000000000000000000000000000000000000000000000000000000000000000000000000000000000000000000000000000000 "
b100000 $
b100000 '
b111 &
#15
b110000100100000011000100110010101100111011010010110111000100000 )
1#
#16
0#
b110111001100100011000110010000001100101011011100110010000100000011001010110111001100100001000000110001001000101010001110110100101101110000000000000000000000000000000000000000000000000000000000000000000000000000000000000000000000000000000000000000000000000 "
b1000101 $
b1000101 '
b1000 &
#17
b11000010010000001100010011001010110011101101001011011100010000001100101 )
1#
#18
0#
b110010001100011001000000110010101101110011001000010000001100101011011100110010000100000011000100100010101000111011010010110111000000000000000000000000000000000000000000000000000000000000000000000000000000000000000000000000000000000000000000000000000000000 "
b1101110 $
b1101110 '
b1001 &
#19
b1100001001000000110001001100101011001110110100101101110001000000110010101101110 )
1#
#20
0#
b110001100100000011001010110111001100100001000000110010101101110011001000010000001100010010001010100011101101001011011100000000000000000000000000000000000000000000000000000000000000000000000000000000000000000000000000000000000000000000000000000000000000000 "
b1100100 $
b1100100 '
b1010 &
#21
1!
b0 *
b110000100100000011000100110010101100111011010010110111000100000011001010110111001100100 )
1#
#22
0#
b10000001100101011011100110010000100000011001010110111001100100001000000110001001000101010001110110100101101110000000000000000000000000000000000000000000000000000000000000000000000000000000000000000000000000000000000000000000000000000000000000000000000000 "
b1100011 $
b1100011 '
b1011 &
#23
0!
b1 *
b11000010010000001100010011001010110011101101001011011100010000001100101011011100110010001100011 )
1#
#24
0#
b110010101101110011001000010000001100101011011100110010000100000011000100100010101000111011010010110111000000000000000000000000000000000000000000000000000000000000000000000000000000000000000000000000000000000000000000000000000000000000000000000000000000000 "
b100000 $
b100000 '
b1100 &
#25
b1100001001000000110001001100101011001110110100101101110001000000110010101101110011001000110001100100000 )
1#
#26
0#
b110111001100100001000000110010101101110011001000010000001100010010001010100011101101001011011100000000000000000000000000000000000000000000000000000000000000000000000000000000000000000000000000000000000000000000000000000000000000000000000000000000000000000 "
b1100101 $
b1100101 '
b1101 &
#27
b110000100100000011000100110010101100111011010010110111000100000011001010110111001100100011000110010000001100101 )
1#
#28
0#
b110010000100000011001010110111001100100001000000110001001000101010001110110100101101110000000000000000000000000000000000000000000000000000000000000000000000000000000000000000000000000000000000000000000000000000000000000000000000000000000000000000000000000 "
b1101110 $
b1101110 '
b1110 &
#29
b11000010010000001100010011001010110011101101001011011100010000001100101011011100110010001100011001000000110010101101110 )
1#
#30
0#
b10000001100101011011100110010000100000011000100100010101000111011010010110111000000000000000000000000000000000000000000000000000000000000000000000000000000000000000000000000000000000000000000000000000000000000000000000000000000000000000000000000000000000 "
b1100100 $
b1100100 '
b1111 &
#31
1!
b0 *
b1100001001000000110001001100101011001110110100101101110001000000110010101101110011001000110001100100000011001010110111001100100 )
1#
#32
0#
b110010101101110011001000010000001100010010001010100011101101001011011100000000000000000000000000000000000000000000000000000000000000000000000000000000000000000000000000000000000000000000000000000000000000000000000000000000000000000000000000000000000000000 "
b100000 $
b100000 '
b10000 &
#33
b110000100100000011000100110010101100111011010010110111000100000011001010110111001100100011000110010000001100101011011100110010000100000 )
1#
#34
0#
b110111001100100001000000110001001000101010001110110100101101110000000000000000000000000000000000000000000000000000000000000000000000000000000000000000000000000000000000000000000000000000000000000000000000000000000000000000000000000000000000000000000000000 "
b1100101 $
b1100101 '
b10001 &
#35
b11000010010000001100010011001010110011101101001011011100010000001100101011011100110010001100011001000000110010101101110011001000010000001100101 )
1#
#36
0#
b110010000100000011000100100010101000111011010010110111000000000000000000000000000000000000000000000000000000000000000000000000000000000000000000000000000000000000000000000000000000000000000000000000000000000000000000000000000000000000000000000000000000000 "
b1101110 $
b1101110 '
b10010 &
#37
b1100001001000000110001001100101011001110110100101101110001000000110010101101110011001000110001100100000011001010110111001100100001000000110010101101110 )
1#
#38
0#
b10000001100010010001010100011101101001011011100000000000000000000000000000000000000000000000000000000000000000000000000000000000000000000000000000000000000000000000000000000000000000000000000000000000000000000000000000000000000000000000000000000000000000 "
b1100100 $
b1100100 '
b10011 &
#39
0!
b11111111111111111111111111111111 *
b110000100100000011000100110010101100111011010010110111000100000011001010110111001100100011000110010000001100101011011100110010000100000011001010110111001100100 )
1#
#40
0#
b110001001000101010001110110100101101110000000000000000000000000000000000000000000000000000000000000000000000000000000000000000000000000000000000000000000000000000000000000000000000000000000000000000000000000000000000000000000000000000000000000000000000000 "
b100000 $
b100000 '
b10100 &
#41
0(
b11000010010000001100010011001010110011101101001011011100010000001100101011011100110010001100011001000000110010101101110011001000010000001100101011011100110010000100000 )
1#
#42
0#
b100010101000111011010010110111000000000000000000000000000000000000000000000000000000000000000000000000000000000000000000000000000000000000000000000000000000000000000000000000000000000000000000000000000000000000000000000000000000000000000000000000000000000 "
b1100010 $
b1100010 '
b10101 &
#43
b1100001001000000110001001100101011001110110100101101110001000000110010101101110011001000110001100100000011001010110111001100100001000000110010101101110011001000010000001100010 )
1#
#44
0#
b100011101101001011011100000000000000000000000000000000000000000000000000000000000000000000000000000000000000000000000000000000000000000000000000000000000000000000000000000000000000000000000000000000000000000000000000000000000000000000000000000000000000000 "
b1000101 $
b1000101 '
b10110 &
#45
b110000100100000011000100110010101100111011010010110111000100000011001010110111001100100011000110010000001100101011011100110010000100000011001010110111001100100001000000110001001100101 )
1#
#46
0#
b110100101101110000000000000000000000000000000000000000000000000000000000000000000000000000000000000000000000000000000000000000000000000000000000000000000000000000000000000000000000000000000000000000000000000000000000000000000000000000000000000000000000000 "
b1000111 $
b1000111 '
b10111 &
#47
b11000010010000001100010011001010110011101101001011011100010000001100101011011100110010001100011001000000110010101101110011001000010000001100101011011100110010000100000011000100110010101100111 )
1#
#48
0#
b110111000000000000000000000000000000000000000000000000000000000000000000000000000000000000000000000000000000000000000000000000000000000000000000000000000000000000000000000000000000000000000000000000000000000000000000000000000000000000000000000000000000000 "
b1101001 $
b1101001 '
b11000 &
#49
b1100001001000000110001001100101011001110110100101101110001000000110010101101110011001000110001100100000011001010110111001100100001000000110010101101110011001000010000001100010011001010110011101101001 )
1#
#50
0#
b0 "
b1101110 $
b1101110 '
b11001 &
#51
b0 *
b110000100100000011000100110010101100111011010010110111000100000011001010110111001100100011000110010000001100101011011100110010000100000011001010110111001100100001000000110001001100101011001110110100101101110 )
1#
#52
0#
b0 $
b0 '
b11010 &
#53
b11000010010000001100010011001010110011101101001011011100010000001100101011011100110010001100011001000000110010101101110011001000010000001100101011011100110010000100000011000100110010101100111011010010110111000100000 )
1#
#54
1!
1(
b0 )
0#
1%
#55
1#
#56
0#
b1100001 $
b1100001 '
b0 &
b10000001000010010001010110011101001001011011100010000001000101011011100110010001100011001000000110010101101110011001000010000001100101011011100110010000100000011000100100010101000111011010010110111000000000000000000000000000000000000000000000000000000000 "
0%
#57
b1100001 )
1#
#58
0#
b100001001000101011001110100100101101110001000000100010101101110011001000110001100100000011001010110111001100100001000000110010101101110011001000010000001100010010001010100011101101001011011100000000000000000000000000000000000000000000000000000000000000000 "
b100000 $
b100000 '
b1 &
#59
b110000100100000 )
1#
#60
0#
b100010101100111010010010110111000100000010001010110111001100100011000110010000001100101011011100110010000100000011001010110111001100100001000000110001001000101010001110110100101101110000000000000000000000000000000000000000000000000000000000000000000000000 "
b1000010 $
b1000010 '
b10 &
#61
b11000010010000001100010 )
1#
#62
0#
b110011101001001011011100010000001000101011011100110010001100011001000000110010101101110011001000010000001100101011011100110010000100000011000100100010101000111011010010110111000000000000000000000000000000000000000000000000000000000000000000000000000000000 "
b1000101 $
b1000101 '
b11 &
#63
b1100001001000000110001001100101 )
1#
#64
0#
b100100101101110001000000100010101101110011001000110001100100000011001010110111001100100001000000110010101101110011001000010000001100010010001010100011101101001011011100000000000000000000000000000000000000000000000000000000000000000000000000000000000000000 "
b1100111 $
b1100111 '
b100 &
#65
b110000100100000011000100110010101100111 )
1#
#66
0#
b110111000100000010001010110111001100100011000110010000001100101011011100110010000100000011001010110111001100100001000000110001001000101010001110110100101101110000000000000000000000000000000000000000000000000000000000000000000000000000000000000000000000000 "
b1001001 $
b1001001 '
b101 &
#67
b11000010010000001100010011001010110011101101001 )
1#
#68
0#
b10000001000101011011100110010001100011001000000110010101101110011001000010000001100101011011100110010000100000011000100100010101000111011010010110111000000000000000000000000000000000000000000000000000000000000000000000000000000000000000000000000000000000 "
b1101110 $
b1101110 '
b110 &
#69
0!
b1 *
b1100001001000000110001001100101011001110110100101101110 )
1#
#70
0#
b100010101101110011001000110001100100000011001010110111001100100001000000110010101101110011001000010000001100010010001010100011101101001011011100000000000000000000000000000000000000000000000000000000000000000000000000000000000000000000000000000000000000000 "
b100000 $
b100000 '
b111 &
#71
b110000100100000011000100110010101100111011010010110111000100000 )
1#
#72
0#
b110111001100100011000110010000001100101011011100110010000100000011001010110111001100100001000000110001001000101010001110110100101101110000000000000000000000000000000000000000000000000000000000000000000000000000000000000000000000000000000000000000000000000 "
b1000101 $
b1000101 '
b1000 &
#73
b11000010010000001100010011001010110011101101001011011100010000001100101 )
1#
#74
0#
b110010001100011001000000110010101101110011001000010000001100101011011100110010000100000011000100100010101000111011010010110111000000000000000000000000000000000000000000000000000000000000000000000000000000000000000000000000000000000000000000000000000000000 "
b1101110 $
b1101110 '
b1001 &
#75
b1100001001000000110001001100101011001110110100101101110001000000110010101101110 )
1#
#76
0#
b110001100100000011001010110111001100100001000000110010101101110011001000010000001100010010001010100011101101001011011100000000000000000000000000000000000000000000000000000000000000000000000000000000000000000000000000000000000000000000000000000000000000000 "
b1100100 $
b1100100 '
b1010 &
#77
1!
b0 *
b110000100100000011000100110010101100111011010010110111000100000011001010110111001100100 )
1#
#78
0#
b10000001100101011011100110010000100000011001010110111001100100001000000110001001000101010001110110100101101110000000000000000000000000000000000000000000000000000000000000000000000000000000000000000000000000000000000000000000000000000000000000000000000000 "
b1100011 $
b1100011 '
b1011 &
#79
0!
b1 *
b11000010010000001100010011001010110011101101001011011100010000001100101011011100110010001100011 )
1#
#80
0#
b110010101101110011001000010000001100101011011100110010000100000011000100100010101000111011010010110111000000000000000000000000000000000000000000000000000000000000000000000000000000000000000000000000000000000000000000000000000000000000000000000000000000000 "
b100000 $
b100000 '
b1100 &
#81
b1100001001000000110001001100101011001110110100101101110001000000110010101101110011001000110001100100000 )
1#
#82
0#
b110111001100100001000000110010101101110011001000010000001100010010001010100011101101001011011100000000000000000000000000000000000000000000000000000000000000000000000000000000000000000000000000000000000000000000000000000000000000000000000000000000000000000 "
b1100101 $
b1100101 '
b1101 &
#83
b110000100100000011000100110010101100111011010010110111000100000011001010110111001100100011000110010000001100101 )
1#
#84
0#
b110010000100000011001010110111001100100001000000110001001000101010001110110100101101110000000000000000000000000000000000000000000000000000000000000000000000000000000000000000000000000000000000000000000000000000000000000000000000000000000000000000000000000 "
b1101110 $
b1101110 '
b1110 &
#85
b11000010010000001100010011001010110011101101001011011100010000001100101011011100110010001100011001000000110010101101110 )
1#
#86
0#
b10000001100101011011100110010000100000011000100100010101000111011010010110111000000000000000000000000000000000000000000000000000000000000000000000000000000000000000000000000000000000000000000000000000000000000000000000000000000000000000000000000000000000 "
b1100100 $
b1100100 '
b1111 &
#87
1!
b0 *
b1100001001000000110001001100101011001110110100101101110001000000110010101101110011001000110001100100000011001010110111001100100 )
1#
#88
0#
b110010101101110011001000010000001100010010001010100011101101001011011100000000000000000000000000000000000000000000000000000000000000000000000000000000000000000000000000000000000000000000000000000000000000000000000000000000000000000000000000000000000000000 "
b100000 $
b100000 '
b10000 &
#89
b110000100100000011000100110010101100111011010010110111000100000011001010110111001100100011000110010000001100101011011100110010000100000 )
1#
#90
0#
b110111001100100001000000110001001000101010001110110100101101110000000000000000000000000000000000000000000000000000000000000000000000000000000000000000000000000000000000000000000000000000000000000000000000000000000000000000000000000000000000000000000000000 "
b1100101 $
b1100101 '
b10001 &
#91
b11000010010000001100010011001010110011101101001011011100010000001100101011011100110010001100011001000000110010101101110011001000010000001100101 )
1#
#92
0#
b110010000100000011000100100010101000111011010010110111000000000000000000000000000000000000000000000000000000000000000000000000000000000000000000000000000000000000000000000000000000000000000000000000000000000000000000000000000000000000000000000000000000000 "
b1101110 $
b1101110 '
b10010 &
#93
b1100001001000000110001001100101011001110110100101101110001000000110010101101110011001000110001100100000011001010110111001100100001000000110010101101110 )
1#
#94
0#
b10000001100010010001010100011101101001011011100000000000000000000000000000000000000000000000000000000000000000000000000000000000000000000000000000000000000000000000000000000000000000000000000000000000000000000000000000000000000000000000000000000000000000 "
b1100100 $
b1100100 '
b10011 &
#95
0!
b11111111111111111111111111111111 *
b110000100100000011000100110010101100111011010010110111000100000011001010110111001100100011000110010000001100101011011100110010000100000011001010110111001100100 )
1#
#96
0#
b110001001000101010001110110100101101110000000000000000000000000000000000000000000000000000000000000000000000000000000000000000000000000000000000000000000000000000000000000000000000000000000000000000000000000000000000000000000000000000000000000000000000000 "
b100000 $
b100000 '
b10100 &
#97
0(
b11000010010000001100010011001010110011101101001011011100010000001100101011011100110010001100011001000000110010101101110011001000010000001100101011011100110010000100000 )
1#
#98
0#
b100010101000111011010010110111000000000000000000000000000000000000000000000000000000000000000000000000000000000000000000000000000000000000000000000000000000000000000000000000000000000000000000000000000000000000000000000000000000000000000000000000000000000 "
b1100010 $
b1100010 '
b10101 &
#99
b1100001001000000110001001100101011001110110100101101110001000000110010101101110011001000110001100100000011001010110111001100100001000000110010101101110011001000010000001100010 )
1#
#100
0#
b100011101101001011011100000000000000000000000000000000000000000000000000000000000000000000000000000000000000000000000000000000000000000000000000000000000000000000000000000000000000000000000000000000000000000000000000000000000000000000000000000000000000000 "
b1000101 $
b1000101 '
b10110 &
#101
b110000100100000011000100110010101100111011010010110111000100000011001010110111001100100011000110010000001100101011011100110010000100000011001010110111001100100001000000110001001100101 )
1#
#102
0#
b110100101101110000000000000000000000000000000000000000000000000000000000000000000000000000000000000000000000000000000000000000000000000000000000000000000000000000000000000000000000000000000000000000000000000000000000000000000000000000000000000000000000000 "
b1000111 $
b1000111 '
b10111 &
#103
b11000010010000001100010011001010110011101101001011011100010000001100101011011100110010001100011001000000110010101101110011001000010000001100101011011100110010000100000011000100110010101100111 )
1#
#104
0#
b110111000000000000000000000000000000000000000000000000000000000000000000000000000000000000000000000000000000000000000000000000000000000000000000000000000000000000000000000000000000000000000000000000000000000000000000000000000000000000000000000000000000000 "
b1101001 $
b1101001 '
b11000 &
#105
b1100001001000000110001001100101011001110110100101101110001000000110010101101110011001000110001100100000011001010110111001100100001000000110010101101110011001000010000001100010011001010110011101101001 )
1#
#106
0#
b0 "
b1101110 $
b1101110 '
b11001 &
#107
b0 *
b110000100100000011000100110010101100111011010010110111000100000011001010110111001100100011000110010000001100101011011100110010000100000011001010110111001100100001000000110001001100101011001110110100101101110 )
1#
#108
0#
b0 $
b0 '
b11010 &
#109
b11000010010000001100010011001010110011101101001011011100010000001100101011011100110010001100011001000000110010101101110011001000010000001100101011011100110010000100000011000100110010101100111011010010110111000100000 )
1#
#110
0#
#111
b1100001001000000110001001100101011001110110100101101110001000000110010101101110011001000110001100100000011001010110111001100100001000000110010101101110011001000010000001100010011001010110011101101001011011100010000000100000 )
1#
#112
0#
#113
b110000100100000011000100110010101100111011010010110111000100000011001010110111001100100011000110010000001100101011011100110010000100000011001010110111001100100001000000110001001100101011001110110100101101110001000000010000000100000 )
1#
#114
0#
#115
b11000010010000001100010011001010110011101101001011011100010000001100101011011100110010001100011001000000110010101101110011001000010000001100101011011100110010000100000011000100110010101100111011010010110111000100000001000000010000000100000 )
1#
#116
0#
#117
b1100001001000000110001001100101011001110110100101101110001000000110010101101110011001000110001100100000011001010110111001100100001000000110010101101110011001000010000001100010011001010110011101101001011011100010000000100000001000000010000000100000 )
1#
#118
0#
#119
b110000100100000011000100110010101100111011010010110111000100000011001010110111001100100011000110010000001100101011011100110010000100000011001010110111001100100001000000110001001100101011001110110100101101110001000000010000000100000001000000010000000100000 )
1#
#120
0#
#121
b10000001100010011001010110011101101001011011100010000001100101011011100110010001100011001000000110010101101110011001000010000001100101011011100110010000100000011000100110010101100111011010010110111000100000001000000010000000100000001000000010000000100000 )
1#
#122
0#
#123
b110001001100101011001110110100101101110001000000110010101101110011001000110001100100000011001010110111001100100001000000110010101101110011001000010000001100010011001010110011101101001011011100010000000100000001000000010000000100000001000000010000000100000 )
1#
#124
0#
#125
b110010101100111011010010110111000100000011001010110111001100100011000110010000001100101011011100110010000100000011001010110111001100100001000000110001001100101011001110110100101101110001000000010000000100000001000000010000000100000001000000010000000100000 )
1#
#126
0#
#127
b110011101101001011011100010000001100101011011100110010001100011001000000110010101101110011001000010000001100101011011100110010000100000011000100110010101100111011010010110111000100000001000000010000000100000001000000010000000100000001000000010000000100000 )
1#
#128
0#
#129
b110100101101110001000000110010101101110011001000110001100100000011001010110111001100100001000000110010101101110011001000010000001100010011001010110011101101001011011100010000000100000001000000010000000100000001000000010000000100000001000000010000000100000 )
1#
#130
0#
#131
b110111000100000011001010110111001100100011000110010000001100101011011100110010000100000011001010110111001100100001000000110001001100101011001110110100101101110001000000010000000100000001000000010000000100000001000000010000000100000001000000010000000100000 )
1#
#132
0#
#133
b10000001100101011011100110010001100011001000000110010101101110011001000010000001100101011011100110010000100000011000100110010101100111011010010110111000100000001000000010000000100000001000000010000000100000001000000010000000100000001000000010000000100000 )
1#
#134
0#
#135
b110010101101110011001000110001100100000011001010110111001100100001000000110010101101110011001000010000001100010011001010110011101101001011011100010000000100000001000000010000000100000001000000010000000100000001000000010000000100000001000000010000000100000 )
1#
#136
0#
#137
b110111001100100011000110010000001100101011011100110010000100000011001010110111001100100001000000110001001100101011001110110100101101110001000000010000000100000001000000010000000100000001000000010000000100000001000000010000000100000001000000010000000100000 )
1#
#138
0#
#139
b110010001100011001000000110010101101110011001000010000001100101011011100110010000100000011000100110010101100111011010010110111000100000001000000010000000100000001000000010000000100000001000000010000000100000001000000010000000100000001000000010000000100000 )
1#
#140
0#
#141
b110001100100000011001010110111001100100001000000110010101101110011001000010000001100010011001010110011101101001011011100010000000100000001000000010000000100000001000000010000000100000001000000010000000100000001000000010000000100000001000000010000000100000 )
1#
#142
0#
#143
b10000001100101011011100110010000100000011001010110111001100100001000000110001001100101011001110110100101101110001000000010000000100000001000000010000000100000001000000010000000100000001000000010000000100000001000000010000000100000001000000010000000100000 )
1#
#144
0#
#145
b110010101101110011001000010000001100101011011100110010000100000011000100110010101100111011010010110111000100000001000000010000000100000001000000010000000100000001000000010000000100000001000000010000000100000001000000010000000100000001000000010000000100000 )
1#
#146
0#
#147
b110111001100100001000000110010101101110011001000010000001100010011001010110011101101001011011100010000000100000001000000010000000100000001000000010000000100000001000000010000000100000001000000010000000100000001000000010000000100000001000000010000000100000 )
1#
#148
0#
#149
b110010000100000011001010110111001100100001000000110001001100101011001110110100101101110001000000010000000100000001000000010000000100000001000000010000000100000001000000010000000100000001000000010000000100000001000000010000000100000001000000010000000100000 )
1#
#150
0#
#151
b10000001100101011011100110010000100000011000100110010101100111011010010110111000100000001000000010000000100000001000000010000000100000001000000010000000100000001000000010000000100000001000000010000000100000001000000010000000100000001000000010000000100000 )
1#
#152
0#
#153
b110010101101110011001000010000001100010011001010110011101101001011011100010000000100000001000000010000000100000001000000010000000100000001000000010000000100000001000000010000000100000001000000010000000100000001000000010000000100000001000000010000000100000 )
1#
#154
0#
#155
b110111001100100001000000110001001100101011001110110100101101110001000000010000000100000001000000010000000100000001000000010000000100000001000000010000000100000001000000010000000100000001000000010000000100000001000000010000000100000001000000010000000100000 )
1#
#156
0#
#157
b110010000100000011000100110010101100111011010010110111000100000001000000010000000100000001000000010000000100000001000000010000000100000001000000010000000100000001000000010000000100000001000000010000000100000001000000010000000100000001000000010000000100000 )
1#
#158
0#
#159
b10000001100010011001010110011101101001011011100010000000100000001000000010000000100000001000000010000000100000001000000010000000100000001000000010000000100000001000000010000000100000001000000010000000100000001000000010000000100000001000000010000000100000 )
1#
#160
0#
#161
b110001001100101011001110110100101101110001000000010000000100000001000000010000000100000001000000010000000100000001000000010000000100000001000000010000000100000001000000010000000100000001000000010000000100000001000000010000000100000001000000010000000100000 )
1#
#162
0#
#163
b110010101100111011010010110111000100000001000000010000000100000001000000010000000100000001000000010000000100000001000000010000000100000001000000010000000100000001000000010000000100000001000000010000000100000001000000010000000100000001000000010000000100000 )
1#
#164
0#
#165
b110011101101001011011100010000000100000001000000010000000100000001000000010000000100000001000000010000000100000001000000010000000100000001000000010000000100000001000000010000000100000001000000010000000100000001000000010000000100000001000000010000000100000 )
1#
#166
0#
#167
b110100101101110001000000010000000100000001000000010000000100000001000000010000000100000001000000010000000100000001000000010000000100000001000000010000000100000001000000010000000100000001000000010000000100000001000000010000000100000001000000010000000100000 )
1#
#168
0#
#169
b110111000100000001000000010000000100000001000000010000000100000001000000010000000100000001000000010000000100000001000000010000000100000001000000010000000100000001000000010000000100000001000000010000000100000001000000010000000100000001000000010000000100000 )
1#
#170
0#
#171
b10000000100000001000000010000000100000001000000010000000100000001000000010000000100000001000000010000000100000001000000010000000100000001000000010000000100000001000000010000000100000001000000010000000100000001000000010000000100000001000000010000000100000 )
1#
