Verilog/05_Pre/11_字符自动机/id_fsm.v
//输入:字符char 时钟clk 输出：out
/*三个状态
    状态1：输入的不是字母
        1.num           保持状态1
        2.alpha         去到状态2
        3.非alpha num   保持状态1
    状态2：字母
        1.num           去到状态3
        2.alpha         保持状态2
        3.非alpha num   去到状态1
    状态3：数字
        1.num           保持状态3
        2.alpha         回到状态2
        3.非alpha num   去到状态1
*/
`define S_00   2'b00
`define S_01   2'b01
`define S_02   2'b10
module id_fsm (
        input [7:0]char,
        input clk,
        output out
    );
    //初始化状态
    reg [1:0]status;
    initial
        status<=`S_00;
    //根据输入的char和当前状态转移状态
    //字母：[65,90] [97,122]    数字：[48,57]
    always@(posedge clk) begin
        case (status)
            `S_00: begin
                status<=((char>=48)&&(char<=57))?`S_00:
                    (((char>=65)&&(char<=90))||((char>=97)&&(char<=122)))?`S_01:
                    `S_00;
                    end
            `S_01: begin
                status<=((char>=48)&&(char<=57))?`S_02:
                    (((char>=65)&&(char<=90))||((char>=97)&&(char<=122)))?`S_01:
                    `S_00;
                    end
            `S_02: begin
                status<=((char>=48)&&(char<=57))?`S_02:
                    (((char>=65)&&(char<=90))||((char>=97)&&(char<=122)))?`S_01:
                    `S_00;
                    end
        endcase
    end
    //判断输出
    assign out=(status==`S_02)?1'b1:1'b0;
endmodule

Verilog/05_Pre/11_字符自动机/tb.v
module tb (
);
//接线
    //输入 char clk
    reg [7:0]char;
    reg clk;
    //输出out
    wire out;
    id_fsm Id_Fsm_My(
        .char(char),
        .clk(clk),
        .out(out)
    );
//生成文件
    initial begin
        $dumpfile("reference.vcd");
        $dumpvars;
    end
//初始化
    initial begin
        clk=0;
        #18 $finish;
    end
//时钟
    always #1 clk=~clk;
//控制输入char
    initial begin
        //abcd
        char=8'd97;
        #2;
        char=8'd98;
        #2;
        char=8'd99;
        #2;
        char=8'd100;
        #2;
        //1234
        char=8'd48;
        #2;
        char=8'd49;
        #2;
        char=8'd50;
        #2;
        char=8'd51;
        #2;
        //*
        char=8'd32;
        #2;
    end
endmodule

Verilog/05_Pre/11_字符自动机/reference.vcd
$date
	Fri Aug 18 02:19:50 2023
$end
$version
	Icarus Verilog
$end
$timescale
	1s
$end
$scope module tb $end
$var wire 1 ! out $end
$var reg 8 " char [7:0] $end
$var reg 1 # clk $end
$scope module Id_Fsm_My $end
$var wire 8 $ char [7:0] $end
$var wire 1 # clk $end
$var wire 1 ! out $end
$var reg 2 % status [1:0] $end
$upscope $end
$upscope $end
$enddefinitions $end
#0
$dumpvars
b0 %
b1100001 $
0#
b1100001 "
0!
$end
#1
b1 %
1#
#2
0#
b1100010 "
b1100010 $
#3
1#
#4
0#
b1100011 "
b1100011 $
#5
1#
#6
0#
b1100100 "
b1100100 $
#7
1#
#8
0#
b110000 "
b110000 $
#9
1!
b10 %
1#
#10
0#
b110001 "
b110001 $
#11
1#
#12
0#
b110010 "
b110010 $
#13
1#
#14
0#
b110011 "
b110011 $
#15
1#
#16
0#
b100000 "
b100000 $
#17
0!
b0 %
1#
