Verilog/07_P1/Q4-格雷码计数器/gray.v
module gray (
    input Clk,Reset,En,
    output [2:0]Output,
    output reg Overflow
);
    reg [2:0]cnt;
    assign Output[0]=cnt[0]^cnt[1];
    assign Output[1]=cnt[1]^cnt[2];
    assign Output[2]=cnt[2];
    initial begin
        cnt<=3'd0;
        Overflow<=1'd0;
    end
    always @(posedge Clk) begin
        if(Reset)begin
            cnt<=3'd0;
            Overflow=1'd0;
        end
        else begin
            if(En)begin
                cnt<=cnt+1'b1;
                if(cnt==3'd7)Overflow<=1'b1;
            end
        end
    end
endmodule //gray

Verilog/07_P1/Q4-格雷码计数器/tb.v
module tb (
);
//接线
    reg Clk,Reset,En;
    wire [2:0]Output;
    wire Overflow;
    gray myGray(
        .Clk(Clk),
        .Reset(Reset),
        .En(En),
        .Output(Output),
        .Overflow(Overflow)
    );
//生成文件
    initial begin
        $dumpfile("reference.vcd");
        $dumpvars;
    end
//初始化
    initial begin
        Clk=0;
        Reset=1;
        En=0;
        #2;
        Reset=0;
        En=1;
        #18 $finish;
    end
//时钟
    always #1 Clk=~Clk;
//控制输入
    // initial begin
    //     #15;
    //     Reset=1;
    //     #2;
    //     Reset=0;
    // end
//
//
//
//
//
//
endmodule

Verilog/07_P1/Q4-格雷码计数器/reference.vcd
$date
	Thu Oct 12 03:26:21 2023
$end
$version
	Icarus Verilog
$end
$timescale
	1s
$end
$scope module tb $end
$var wire 1 ! Overflow $end
$var wire 3 " Output [2:0] $end
$var reg 1 # Clk $end
$var reg 1 $ En $end
$var reg 1 % Reset $end
$scope module myGray $end
$var wire 1 # Clk $end
$var wire 1 $ En $end
$var wire 1 % Reset $end
$var wire 3 & Output [2:0] $end
$var reg 1 ! Overflow $end
$var reg 3 ' cnt [2:0] $end
$upscope $end
$upscope $end
$enddefinitions $end
#0
$dumpvars
b0 '
b0 &
1%
0$
0#
b0 "
0!
$end
#1
1#
#2
0#
1$
0%
#3
b1 "
b1 &
b1 '
1#
#4
0#
#5
b11 "
b11 &
b10 '
1#
#6
0#
#7
b10 "
b10 &
b11 '
1#
#8
0#
#9
b110 "
b110 &
b100 '
1#
#10
0#
#11
b111 "
b111 &
b101 '
1#
#12
0#
#13
b101 "
b101 &
b110 '
1#
#14
0#
#15
b100 "
b100 &
b111 '
1#
#16
0#
#17
b0 "
b0 &
1!
b0 '
1#
#18
0#
#19
b1 "
b1 &
b1 '
1#
