Verilog/05_Pre/04_状态机_112233有效/counting.v
//输入：num clk 输出：ans
//4个状态
`define S_00 2'b00
`define S_01 2'b01
`define S_02 2'b10
`define S_03 2'b11
//模块
module counting (
        input [1:0]num,
        input clk,
        output ans
    );
    //初始化状态
    reg [1:0]status;
    initial
        status<=`S_00;
    //根据状态和num状态转移
    always@(posedge clk) begin
        case (status)
            `S_00: begin
                case (num)
                    2'b01:
                        status<=`S_01;
                    2'b10:
                        status<=`S_00;
                    2'b11:
                        status<=`S_00;
                    default:
                        status<=`S_00;
                endcase
            end
            `S_01: begin
                case (num)
                    2'b01:
                        status<=`S_01;
                    2'b10:
                        status<=`S_02;
                    2'b11:
                        status<=`S_00;
                    default:
                        status<=`S_00;
                endcase
            end
            `S_02: begin
                case (num)
                    2'b01:
                        status<=`S_01;
                    2'b10:
                        status<=`S_02;
                    2'b11:
                        status<=`S_03;
                    default:
                        status<=`S_00;
                endcase
            end
            `S_03: begin
                case (num)
                    2'b01:
                        status<=`S_01;
                    2'b10:
                        status<=`S_00;
                    2'b11:
                        status<=`S_03;
                    default:
                        status<=`S_00;
                endcase
            end
        endcase
    end
    //输出ans
    assign ans=(status==`S_03)?1'b1:1'b0;
endmodule
//
//
//
//
//
//
//

Verilog/05_Pre/04_状态机_112233有效/tb.v
module tb (
);
//接线
    //输入和时钟都要reg
    reg [1:0]num;
    reg clk;
    //输出wire
    wire ans;
    counting Counting_My(
        .num(num),
        .clk(clk),
        .ans(ans)
    );
//
//
//生成文件
    initial begin
        $dumpfile("reference.vcd");
        $dumpvars;
    end
//初始化
    initial begin
        clk=1'b0;
        #32 $finish;
    end
//时钟
    always #1 clk=~clk;
//输入数字
    initial begin
        //1 1 2 3 3
        //1 2 1 1 1 
        //2 2 3 3 3 
        //1
        num=2'b01;
        #2;
        num=2'b01;
        #2;
        num=2'b10;
        #2;
        num=2'b11;
        #2;
        num=2'b11;
        #2;

        num=2'b01;
        #2;
        num=2'b10;
        #2;
        num=2'b01;
        #2;
        num=2'b01;
        #2;
        num=2'b01;
        #2;

        num=2'b10;
        #2;
        num=2'b10;
        #2;
        num=2'b11;
        #2;
        num=2'b11;
        #2;
        num=2'b11;
        #2;
        
        num=2'b01;
        #2;
    end
endmodule

Verilog/05_Pre/04_状态机_112233有效/reference.vcd
$date
	Thu Aug 17 22:39:32 2023
$end
$version
	Icarus Verilog
$end
$timescale
	1s
$end
$scope module tb $end
$var wire 1 ! ans $end
$var reg 1 " clk $end
$var reg 2 # num [1:0] $end
$scope module Counting_My $end
$var wire 1 " clk $end
$var wire 2 $ num [1:0] $end
$var wire 1 ! ans $end
$var reg 2 % status [1:0] $end
$upscope $end
$upscope $end
$enddefinitions $end
#0
$dumpvars
b0 %
b1 $
b1 #
0"
0!
$end
#1
b1 %
1"
#2
0"
#3
1"
#4
0"
b10 #
b10 $
#5
b10 %
1"
#6
0"
b11 #
b11 $
#7
1!
b11 %
1"
#8
0"
#9
1"
#10
0"
b1 #
b1 $
#11
0!
b1 %
1"
#12
0"
b10 #
b10 $
#13
b10 %
1"
#14
0"
b1 #
b1 $
#15
b1 %
1"
#16
0"
#17
1"
#18
0"
#19
1"
#20
0"
b10 #
b10 $
#21
b10 %
1"
#22
0"
#23
1"
#24
0"
b11 #
b11 $
#25
1!
b11 %
1"
#26
0"
#27
1"
#28
0"
#29
1"
#30
0"
b1 #
b1 $
#31
0!
b1 %
1"
