Verilog/07_P1/Q5-F序列检测/expr.v
module expr (
    input clk,clr,
    input [7:0]in,
    output out
);
    reg [1:0]my_state;
    initial begin
        my_state<=2'd0;
    end
    //状转
    always @(posedge clk,clr) begin
        if(clr)begin
            my_state<=2'd0;
        end
        else if(clk) begin
            case (my_state)
                2'd0:begin
                    if((in>="0")&&(in<="9"))begin
                        my_state<=2'd1;
                    end
                    else begin
                        my_state<=2'd3;
                    end
                end 
                2'd1:begin
                    if((in=="+")||(in=="*"))begin
                        my_state<=2'd2;
                    end
                    else begin
                        my_state<=2'd3;
                    end
                end
                2'd2:begin
                    if((in>="0")&&(in<="9"))begin
                        my_state<=2'd1;
                    end
                    else begin
                        my_state<=2'd3;
                    end
                end
                2'd3:begin
                    my_state<=2'd3;
                end
            endcase
        end
    end
    //根据当前状态输出
    assign out = (my_state==2'd1)?1:
                    0;
endmodule

Verilog/07_P1/Q5-F序列检测/tb.v
module tb (
);
//接线
    reg clk,clr;
    reg [7:0]in;
    wire out;
    expr myExpr(
        .clk(clk),
        .clr(clr),
        .in(in),
        .out(out)
    );
//生成文件
    initial begin
        $dumpfile("reference.vcd");
        $dumpvars;
    end
//初始化
    initial begin
        clk=0;

        clr=1;
        #2;
        clr=0;

        #30 $finish;
    end
//时钟
    always #1 clk=~clk;
//控制输入
    initial begin
        #2;

        in="1";
        #2 in="+";
        #2 in="2";
        #2 in="+";
        #2 in="3";
        #2 in="+";
        #2 in="4";
        #2;

        clr=1;
        #2;
        clr=0;

        #2 in="1";
        #2 in="+";
        #2 in="+";
        #2 in="2";
        #2;
    end
endmodule

Verilog/07_P1/Q5-F序列检测/reference.vcd
$date
	Thu Oct 12 08:26:29 2023
$end
$version
	Icarus Verilog
$end
$timescale
	1s
$end
$scope module tb $end
$var wire 1 ! out $end
$var reg 1 " clk $end
$var reg 1 # clr $end
$var reg 8 $ in [7:0] $end
$scope module myExpr $end
$var wire 1 " clk $end
$var wire 1 # clr $end
$var wire 8 % in [7:0] $end
$var wire 1 ! out $end
$var reg 2 & my_state [1:0] $end
$upscope $end
$upscope $end
$enddefinitions $end
#0
$dumpvars
b0 &
bx %
bx $
1#
0"
0!
$end
#1
1"
#2
0"
b110001 $
b110001 %
0#
#3
1!
b1 &
1"
#4
0"
b101011 $
b101011 %
#5
0!
b10 &
1"
#6
0"
b110010 $
b110010 %
#7
1!
b1 &
1"
#8
0"
b101011 $
b101011 %
#9
0!
b10 &
1"
#10
0"
b110011 $
b110011 %
#11
1!
b1 &
1"
#12
0"
b101011 $
b101011 %
#13
0!
b10 &
1"
#14
0"
b110100 $
b110100 %
#15
1!
b1 &
1"
#16
0!
b0 &
0"
1#
#17
1"
#18
0"
0#
#19
1!
b1 &
1"
#20
0"
b110001 $
b110001 %
#21
0!
b11 &
1"
#22
0"
b101011 $
b101011 %
#23
1"
#24
0"
#25
1"
#26
0"
b110010 $
b110010 %
