Verilog/05_Pre/14_长字符判断+错误位置判断/local/cpu_checker.v

`define S_00 5'd0
`define S_01 5'd1
`define S_02 5'd2
`define S_03 5'd3
`define S_04 5'd4
`define S_05 5'd5
`define S_06 5'd6
`define S_07 5'd7
`define S_08 5'd8
`define S_09 5'd9
`define S_10 5'd10
`define S_11 5'd11
`define S_12 5'd12
`define S_13 5'd13
`define S_14 5'd14
`define S_15 5'd15
`define S_16 5'd16
`define S_17 5'd17
`define S_18 5'd18
`define S_19 5'd19
`define S_20 5'd20
`define S_25 5'd25
`define S_27 5'd27
`define S_29 5'd29

module cpu_checker (
    input clk,
    input reset,
    input [7:0]char,
    input [15:0]freq,
    output [1:0]format_type,
    output reg [3:0]error_code,
    output [31:0]test_pc,
    output [15:0]test_grf,
    output [31:0]test_addr
);
    
    reg [4:0]my_states;
    reg [2:0]cnt_up8;
    reg [1:0]cnt_up4;
    reg [7:0]my_time[3:0];
    reg [7:0]pc[7:0];
    reg [7:0]grf[3:0];//$
    reg [7:0]addr[7:0];//
    integer i;
    
    //计算time
    wire [15:0]time_cal[3:0];
    wire [15:0]time_result;
    assign time_cal[0]=  {
            3'd0,my_time[0][3:0],9'd0
        }|{
            4'd0,my_time[0][3:0],8'd0
        }|{
            5'd0,my_time[0][3:0],7'd0
        }|{
            6'd0,my_time[0][3:0],6'd0
        }|{
            7'd0,my_time[0][3:0],5'd0
        }|{
            9'd0,my_time[0][3:0],3'd0
        };//相当于time[0]1000
    assign time_cal[1]=  {
            6'd0,my_time[1][3:0],6'd0
        }|{
            7'd0,my_time[1][3:0],5'd0
        }|{
            10'd0,my_time[1][3:0],2'd0
        };//相当于time[1]100
    assign time_cal[2]=  {
            8'd0,my_time[2][3:0],3'd0
        }|{
            11'd0,my_time[2][3:0],1'b0
        };//相当于time[2]10
    assign time_cal[3]=my_time[3];
    assign time_result=time_cal[0]+time_cal[1]+time_cal[2]+time_cal[3];

    integer pos01;
    integer pos02;
    always @(format_type) begin
        while(freq[pos01]==1'b0)begin
            pos01=pos01+1;
        end
        
        for(pos02=0;pos02<pos01-1;pos02=pos02+1)begin
            if((time_result[pos02]==1'b1)&&(format_type!=2'd0))error_code[0]=1'b1;
            if(format_type==2'd0)error_code[0]=1'b0;
        end
    end

    //计算pc
    wire [31:0]pc_result={
        pc[0][3:0],pc[1][3:0],pc[2][3:0],pc[3][3:0],pc[4][3:0],pc[5][3:0],pc[6][3:0],pc[7][3:0]
    };
    assign test_pc=pc_result;
    wire pc_legal;
    assign pc_legal=(pc_result>=32'h00003000)&(pc_result<=32'h00004fff)&(pc_result[1:0]==2'b00);
    always @(format_type) begin
        error_code[1]=(format_type!=2'd0)&(~pc_legal);
    end

    assign format_type = (my_states==`S_10)?2'b01:
                        (my_states==`S_20)?2'b10:
                        2'b00;

    //计算$后的数字为0-31
    wire [15:0]grf_cal[3:0];
    wire [15:0]grf_result;
    assign grf_cal[0]=  {
            3'd0,grf[0][3:0],9'd0
        }|{
            4'd0,grf[0][3:0],8'd0
        }|{
            5'd0,grf[0][3:0],7'd0
        }|{
            6'd0,grf[0][3:0],6'd0
        }|{
            7'd0,grf[0][3:0],5'd0
        }|{
            9'd0,grf[0][3:0],3'd0
        };//相当于grf[0]1000
    assign grf_cal[1]=  {
            6'd0,grf[1][3:0],6'd0
        }|{
            7'd0,grf[1][3:0],5'd0
        }|{
            10'd0,grf[1][3:0],2'd0
        };//相当于grf[1]100
    assign grf_cal[2]=  {
            8'd0,grf[2][3:0],3'd0
        }|{
            11'd0,grf[2][3:0],1'b0
        };//相当于grf[2]10
    assign grf_cal[3]=grf[3];
    assign grf_result=grf_cal[0]+grf_cal[1]+grf_cal[2]+grf_cal[3];
    assign test_grf=grf_result;
    wire grf_legal;
    assign grf_legal=(grf_result>=0)&(grf_result<=31);
    always @(format_type) begin
        error_code[3]=(format_type==2'd1)&(~grf_legal);
    end

    //计算后的addr
    wire [31:0]addr_result={
        addr[0][3:0],addr[1][3:0],addr[2][3:0],addr[3][3:0],addr[4][3:0],addr[5][3:0],addr[6][3:0],addr[7][3:0]
    };
    assign test_addr=addr_result;
    wire addr_legal;
    assign addr_legal=(addr_result>=32'h00000000)&(addr_result<=32'h00002fff)&(addr_result[1:0]==2'b00);
    always @(format_type) begin
        error_code[2]=(format_type==2'd2)&(~addr_legal);
    end

    assign format_type = (my_states==`S_10)?2'b01:
                        (my_states==`S_20)?2'b10:
                        2'b00;


    always @(posedge clk) begin
        if(reset)begin
            my_states<=`S_00;
            cnt_up8<=3'd0;
            cnt_up4<=2'd0;
            for(i=0;i<4;i=i+1)begin
                my_time[i]<=8'd0;
                grf[i]<=8'd0;
            end
            for(i=0;i<8;i=i+1)begin
                pc[i]<=8'd0;
                addr[i]<=8'd0;
            end
            error_code<=4'd0;
            pos01<=32'd0;
            pos02<=32'd0;
        end
        else begin
            case (my_states)
                `S_00: begin
                    my_states<=(char=="^")?`S_01:
                                `S_00;
                    cnt_up8<=3'd0;
                    cnt_up4<=2'd0;
                    for(i=0;i<4;i=i+1)begin
                        my_time[i]<=8'd0;
                        grf[i]<=8'd0;
                    end
                    for(i=0;i<8;i=i+1)begin
                        pc[i]<=8'd0;
                        addr[i]<=8'd0;
            end
                end
                `S_01:begin
                    if(char>="0"&&char<="9")begin
                        my_states<=`S_02;
                        cnt_up4<=2'd1;
                        my_time[cnt_up4]<=char-"0";
                    end
                    else begin
                        my_states<=(char=="^")?`S_01:
                                `S_00;
                    end
                end
                `S_02:begin
                    if(char>="0"&&char<="9")begin
                        cnt_up4<=cnt_up4+2'd1;
                        my_time[cnt_up4]<=char-"0";
                        if(cnt_up4==2'd0)my_states<=`S_00;
                        else my_states<=`S_02;
                    end
                    else if(char=="@")begin
                        my_states<=`S_25;
                        cnt_up4<=2'd0;
                        cnt_up8<=3'd0;
                    end
                    else begin
                        my_states<=(char=="^")?`S_01:
                                `S_00;
                    end
                end
                `S_25:begin
                    if(((char>="0")&&(char<="9"))||((char>="a")&&(char<="f")))begin
                        cnt_up8<=3'd1;
                        if((char>="0")&&(char<="9"))begin
                            pc[cnt_up8]<=char-"0";
                        end
                        else begin
                            pc[cnt_up8]<=char-"a"+10;
                        end
                        my_states<=`S_03;
                    end
                    else begin
                        my_states<=(char=="^")?`S_01:
                                `S_00;
                    end
                end
                `S_03:begin
                    if(((char>="0")&&(char<="9"))||((char>="a")&&(char<="f")))begin
                        cnt_up8<=cnt_up8+3'd1;
                        if((char>="0")&&(char<="9"))begin
                            pc[cnt_up8]<=char-"0";
                            end
                        else begin
                            pc[cnt_up8]<=char-"a"+10;
                            end
                        if(cnt_up8==3'd0)my_states<=`S_00;
                        else my_states<=`S_03;
                    end
                    else if((char==":")&&(cnt_up8==3'd0))begin
                        my_states<=`S_04;
                    end
                    else begin
                        my_states<=(char=="^")?`S_01:
                                `S_00;
                    end
                end
                `S_04:begin
                    my_states<= (char==" ")?`S_04:
                                (char=="$")?`S_27:
                                (char==8'd42)?`S_29:
                                (char=="^")?`S_01:
                                `S_00;
                end
                `S_27:begin
                    if(char>="0"&&char<="9")begin
                        cnt_up4<=2'd1;
                        grf[cnt_up4]<=char-"0";
                        my_states<=`S_05;
                    end
                    else begin
                        my_states<=(char=="^")?`S_01:
                                    `S_00;
                    end
                end
                `S_05:begin
                    if(char>="0"&&char<="9")begin
                        cnt_up4<=cnt_up4+2'd1;
                        grf[cnt_up4]<=char-"0";
                        if(cnt_up4==2'd0)my_states<=`S_00;
                        else my_states<=`S_05;
                    end
                    else if(char==" ")begin
                        my_states<=`S_06;
                        cnt_up4<=2'd0;
                        cnt_up8<=3'd0;
                    end
                    else if(char=="<")begin
                        my_states<=`S_07;
                        cnt_up4<=2'd0;
                        cnt_up8<=3'd0;
                    end
                    else begin
                        my_states<=(char=="^")?`S_01:
                                `S_00;
                    end
                end
                `S_06:begin
                    if(char==" ")begin
                        my_states<=`S_06;
                    end
                    else if(char=="<")begin
                        my_states<=`S_07;
                    end
                    else begin
                         my_states<=(char=="^")?`S_01:
                                `S_00;
                    end
                end
                `S_07:begin
                    if(char=="=")begin
                        my_states<=`S_08;
                    end
                    else begin
                        my_states<=(char=="^")?`S_01:
                                `S_00;
                    end
                end
                `S_08:begin
                    if(char==" ")begin
                        my_states<=`S_08;
                    end
                    else if(((char>="0")&&(char<="9"))||((char>="a")&&(char<="f")))begin
                        my_states<=`S_09;
                        cnt_up8<=3'd1;
                    end
                    else begin
                        my_states<=(char=="^")?`S_01:
                                `S_00;
                    end
                end
                `S_09:begin
                    if(((char>="0")&&(char<="9"))||((char>="a")&&(char<="f")))begin
                        cnt_up8<=cnt_up8+3'd1;
                        if(cnt_up8==3'd0)my_states<=`S_00;
                        else my_states<=`S_09;
                    end
                    else if((char=="#")&&(cnt_up8==3'd0))begin
                        my_states<=`S_10;
                    end
                    else begin
                        my_states<=(char=="^")?`S_01:
                                `S_00;
                    end
                end
                `S_10:begin
                    my_states<=(char=="^")?`S_01:
                                `S_00;
                end
                `S_29:begin
                    if(((char>="0")&&(char<="9"))||((char>="a")&&(char<="f")))begin
                        cnt_up8<=3'd1;
                        if((char>="0")&&(char<="9"))begin
                            addr[cnt_up8]<=char-"0";
                            end
                        else begin
                            addr[cnt_up8]<=char-"a"+10;
                        end
                        my_states<=`S_15;
                    end
                    else begin
                        my_states<=(char=="^")?`S_01:
                                `S_00;
                    end
                end
                `S_15:begin
                    if(((char>="0")&&(char<="9"))||((char>="a")&&(char<="f")))begin
                        cnt_up8<=cnt_up8+3'd1;
                        if((char>="0")&&(char<="9"))begin
                            addr[cnt_up8]<=char-"0";
                            end
                        else begin
                            addr[cnt_up8]<=char-"a"+10;
                        end
                        if(cnt_up8==3'd0)my_states<=`S_00;
                        else my_states<=`S_15;
                    end
                    else if((char==" ")&&(cnt_up8==3'd0))begin
                        my_states<=`S_16;
                    end
                    else if((char=="<")&&(cnt_up8==3'd0))begin
                        my_states<=`S_17;
                    end
                    else begin
                        my_states<=(char=="^")?`S_01:
                                `S_00;
                    end
                end
                `S_16:begin
                    my_states<= (char==" ")?`S_16:
                                (char=="<")?`S_17:
                                (char=="^")?`S_01:
                                `S_00;
                end
                `S_17:begin
                    my_states<= (char=="=")?`S_18:
                                (char=="^")?`S_01:
                                `S_00;
                end
                `S_18:begin
                    if(char==" ")begin
                        my_states<=`S_18;
                    end
                    else if(((char>="0")&&(char<="9"))||((char>="a")&&(char<="f")))begin
                        cnt_up8<=3'd1;
                        my_states<=`S_19;
                    end
                    else begin
                        my_states<=(char=="^")?`S_01:
                                `S_00;
                    end
                end
                `S_19:begin
                    if(((char>="0")&&(char<="9"))||((char>="a")&&(char<="f")))begin
                        cnt_up8<=cnt_up8+3'd1;
                        if(cnt_up8==3'd0)my_states<=`S_00;
                        else my_states<=`S_19;
                    end
                    else if((char=="#")&&(cnt_up8==3'd0))begin
                        my_states<=`S_20;
                    end
                    else begin
                        my_states<=(char=="^")?`S_01:
                                `S_00;
                    end
                end
                `S_20:begin
                     my_states<=(char=="^")?`S_01:
                                `S_00;
                end
                default: my_states<=`S_00;
            endcase
        end
    end

endmodule

Verilog/05_Pre/14_长字符判断+错误位置判断/local/tb.v
module tb (
);
//接线
    reg clk,reset;
    reg [7:0]char;
    reg [15:0]freq;
    wire [1:0]format_type;
    wire [3:0]error_code;
    wire [31:0]test_pc;
    wire [15:0]test_grf;
    wire [31:0]test_addr;
    cpu_checker CPU_Checker_My(
        .clk(clk),
        .reset(reset),
        .char(char),
        .freq(freq),
        .format_type(format_type),
        .error_code(error_code),
        .test_pc(test_pc),
        .test_grf(test_grf),
        .test_addr(test_addr)
    );
//
//
//生成文件
    initial begin
        $dumpfile("reference.vcd");
        $dumpvars;
    end
//初始化
    initial begin
        clk=0;
        reset=1;
        freq=2048;
        #2;
        reset=0;
        #120 $finish;
    end
//时钟
    always #1 clk=~clk;
//控制输入
    initial begin
        #2 char="^";
        #2 char="1";
        #2 char="0";
        #2 char="2";
        #2 char="4";
        #2 char="@";
        #2 char="0";
        #2 char="0";
        #2 char="0";
        #2 char="0";
        #2 char="4";
        #2 char="f";
        #2 char="f";
        #2 char="0";
        #2 char=":";
        #2 char=" ";
        #2 char="*";
        #2 char="0";
        #2 char="0";
        #2 char="0";
        #2 char="0";
        #2 char="0";
        #2 char="0";
        #2 char="0";
        #2 char="0";
        #2 char=" ";
        #2 char="<";
        #2 char="=";
        #2 char=" ";
        #2 char="0";
        #2 char="0";
        #2 char="0";
        #2 char="0";
        #2 char="0";
        #2 char="0";
        #2 char="0";
        #2 char="0";
        #2 char="#";
    end
//
//
//
//
//
//
endmodule

Verilog/05_Pre/14_长字符判断+错误位置判断/local/reference.vcd
$date
	Thu Sep 21 08:24:51 2023
$end
$version
	Icarus Verilog
$end
$timescale
	1s
$end
$scope module tb $end
$var wire 2 ! format_type [1:0] $end
$var wire 32 " test_pc [31:0] $end
$var wire 16 # test_grf [15:0] $end
$var wire 32 $ test_addr [31:0] $end
$var wire 4 % error_code [3:0] $end
$var reg 8 & char [7:0] $end
$var reg 1 ' clk $end
$var reg 16 ( freq [15:0] $end
$var reg 1 ) reset $end
$scope module CPU_Checker_My $end
$var wire 1 * addr_legal $end
$var wire 8 + char [7:0] $end
$var wire 1 ' clk $end
$var wire 2 , format_type [1:0] $end
$var wire 16 - freq [15:0] $end
$var wire 1 . grf_legal $end
$var wire 1 / pc_legal $end
$var wire 1 ) reset $end
$var wire 32 0 test_addr [31:0] $end
$var wire 16 1 test_grf [15:0] $end
$var wire 32 2 test_pc [31:0] $end
$var wire 16 3 time_result [15:0] $end
$var wire 32 4 pc_result [31:0] $end
$var wire 16 5 grf_result [15:0] $end
$var wire 32 6 addr_result [31:0] $end
$var reg 2 7 cnt_up4 [1:0] $end
$var reg 3 8 cnt_up8 [2:0] $end
$var reg 4 9 error_code [3:0] $end
$var reg 5 : my_states [4:0] $end
$var integer 32 ; i [31:0] $end
$var integer 32 < pos01 [31:0] $end
$var integer 32 = pos02 [31:0] $end
$upscope $end
$upscope $end
$enddefinitions $end
#0
$dumpvars
b0 =
bx <
bx ;
bx :
bx 9
bx 8
bx 7
bx 6
bx 5
bx 4
bx 3
bx 2
bx 1
bx 0
x/
x.
b100000000000 -
bx ,
bx +
x*
1)
b100000000000 (
0'
bx &
bx %
bx $
bx #
bx "
bx !
$end
#1
1.
b0 #
b0 1
b0 5
b0 3
1*
0/
b1010 =
b0 $
b0 0
b0 6
b0 "
b0 2
b0 4
b0 !
b0 ,
b1011 <
b0 %
b0 9
b0 7
b0 8
b0 :
b1000 ;
1'
#2
0'
b1011110 &
b1011110 +
0)
#3
b1 :
b1000 ;
1'
#4
0'
b110001 &
b110001 +
#5
b1010 =
b1111101000 3
b1 7
b10 :
1'
#6
0'
b110000 &
b110000 +
#7
b10 7
1'
#8
0'
b110010 &
b110010 +
#9
b1010 =
b1111111100 3
b11 7
1'
#10
0'
b110100 &
b110100 +
#11
b1010 =
b10000000000 3
b0 7
1'
#12
0'
b1000000 &
b1000000 +
#13
b11001 :
1'
#14
0'
b110000 &
b110000 +
#15
b11 :
b1 8
1'
#16
0'
#17
b10 8
1'
#18
0'
#19
b11 8
1'
#20
0'
#21
b100 8
1'
#22
0'
b110100 &
b110100 +
#23
1/
b100000000000000 "
b100000000000000 2
b100000000000000 4
b101 8
1'
#24
0'
b1100110 &
b1100110 +
#25
b100111100000000 "
b100111100000000 2
b100111100000000 4
b110 8
1'
#26
0'
#27
b100111111110000 "
b100111111110000 2
b100111111110000 4
b111 8
1'
#28
0'
b110000 &
b110000 +
#29
b0 8
1'
#30
0'
b111010 &
b111010 +
#31
b100 :
1'
#32
0'
b100000 &
b100000 +
#33
1'
#34
0'
b101010 &
b101010 +
#35
b11101 :
1'
#36
0'
b110000 &
b110000 +
#37
b1111 :
b1 8
1'
#38
0'
#39
b10 8
1'
#40
0'
#41
b11 8
1'
#42
0'
#43
b100 8
1'
#44
0'
#45
b101 8
1'
#46
0'
#47
b110 8
1'
#48
0'
#49
b111 8
1'
#50
0'
#51
b0 8
1'
#52
0'
b100000 &
b100000 +
#53
b10000 :
1'
#54
0'
b111100 &
b111100 +
#55
b10001 :
1'
#56
0'
b111101 &
b111101 +
#57
b10010 :
1'
#58
0'
b100000 &
b100000 +
#59
1'
#60
0'
b110000 &
b110000 +
#61
b10011 :
b1 8
1'
#62
0'
#63
b10 8
1'
#64
0'
#65
b11 8
1'
#66
0'
#67
b100 8
1'
#68
0'
#69
b101 8
1'
#70
0'
#71
b110 8
1'
#72
0'
#73
b111 8
1'
#74
0'
#75
b0 8
1'
#76
0'
b100011 &
b100011 +
#77
b1010 =
b10 !
b10 ,
b10100 :
1'
#78
0'
#79
b1010 =
b0 !
b0 ,
b0 :
1'
#80
0'
#81
0/
b0 "
b0 2
b0 4
b1010 =
b0 3
b1000 ;
1'
#82
0'
#83
b1000 ;
1'
#84
0'
#85
b1000 ;
1'
#86
0'
#87
b1000 ;
1'
#88
0'
#89
b1000 ;
1'
#90
0'
#91
b1000 ;
1'
#92
0'
#93
b1000 ;
1'
#94
0'
#95
b1000 ;
1'
#96
0'
#97
b1000 ;
1'
#98
0'
#99
b1000 ;
1'
#100
0'
#101
b1000 ;
1'
#102
0'
#103
b1000 ;
1'
#104
0'
#105
b1000 ;
1'
#106
0'
#107
b1000 ;
1'
#108
0'
#109
b1000 ;
1'
#110
0'
#111
b1000 ;
1'
#112
0'
#113
b1000 ;
1'
#114
0'
#115
b1000 ;
1'
#116
0'
#117
b1000 ;
1'
#118
0'
#119
b1000 ;
1'
#120
0'
#121
b1000 ;
1'
